pycloc/CLOC.py
pycloc/__init__.py
pycloc/utils/CLOCException.py
pycloc/utils/__init__.py
pycloctest-0.0.3.dist-info/LICENSE
pycloctest-0.0.3.dist-info/METADATA
pycloctest-0.0.3.dist-info/WHEEL
pycloctest-0.0.3.dist-info/top_level.txt
pycloctest-0.0.3.dist-info/RECORD
